qoqo_tket/__init__.py
qoqo_tket/qoqo_tket.py
qoqo_tket-2.0.0.dist-info/licenses/LICENSE
qoqo_tket-2.0.0.dist-info/METADATA
qoqo_tket-2.0.0.dist-info/WHEEL
qoqo_tket-2.0.0.dist-info/top_level.txt
qoqo_tket-2.0.0.dist-info/RECORD
