Metadata-Version: 2.4
Name: qoqo-tket
Version: 2.0.0
Author-email: HQS Quantum Simulation GmbH <info@quantumsimulations.de>
Maintainer-email: HQS Quantum Simulations GmbH <info@quantumsimulations.de>
License:                                  Apache License
Requires-Python: >=3.10
License-File: LICENSE
Requires-Dist: pydantic
Requires-Dist: qoqo>=1.19
Requires-Dist: qoqo_qasm>=0.14.0
Requires-Dist: pytket<3.0,>=2.4
Requires-Dist: pytket-qiskit>=0.5
Requires-Dist: qiskit<1.3,>=1.0
Requires-Dist: qiskit-algorithms<0.4,>=0.3.0
Requires-Dist: qiskit-ibm-runtime<0.36,>=0.35.0
Requires-Dist: qiskit-aer>=0.16
Requires-Dist: numpy>=2.0
Provides-Extra: tests
Requires-Dist: coverage; extra == "tests"
Requires-Dist: pytest; extra == "tests"
Requires-Dist: pytket-projectq; extra == "tests"
Provides-Extra: dev
Requires-Dist: bandit; extra == "dev"
Requires-Dist: black; extra == "dev"
Requires-Dist: mypy; extra == "dev"
Requires-Dist: ruff; extra == "dev"
Requires-Dist: sphinx; extra == "dev"
Requires-Dist: sphinx_rtd_theme; extra == "dev"
Requires-Dist: nbsphinx; extra == "dev"
Provides-Extra: docs
Requires-Dist: sphinx>=2.1; extra == "docs"
Requires-Dist: nbsphinx; extra == "docs"
Requires-Dist: pygments; extra == "docs"
Requires-Dist: recommonmark; extra == "docs"
Requires-Dist: myst_parser; extra == "docs"
Requires-Dist: sphinx_rtd_theme; extra == "docs"
Requires-Dist: tomli; extra == "docs"
Dynamic: license-file
